CONTRIBUTING.txt
CONTRIBUTORS.txt
COPYING
MANIFEST.in
NEWS.txt
README.rst
pycard.conf.sample
setup.py
bin/pc_query
bin/pycard-import
bin/pycardsyncer
doc/man/pc_query.1
doc/man/pycard-import.1
doc/man/pycardsyncer.1
pyCardDAV.egg-info/PKG-INFO
pyCardDAV.egg-info/SOURCES.txt
pyCardDAV.egg-info/dependency_links.txt
pyCardDAV.egg-info/requires.txt
pyCardDAV.egg-info/top_level.txt
pycarddav/__init__.py
pycarddav/backend.py
pycarddav/carddav.py
pycarddav/model.py
pycarddav/ui.py
pycarddav/version.py
pycarddav/controllers/__init__.py
pycarddav/controllers/query.py
pycarddav/controllers/sync.py