Metadata-Version: 1.1
Name: pyCardDAV
Version: 0.7.0
Summary: A CardDAV based address book tool
Home-page: http://lostpackets.de/pycarddav/
Author: Christian Geier
Author-email: pycarddav@lostpackets.de
License: Expat/MIT
Platform: UNKNOWN
Classifier: Development Status :: 4 - Beta
Classifier: License :: OSI Approved :: MIT License
Classifier: Environment :: Console :: Curses
Classifier: Intended Audience :: End Users/Desktop
Classifier: Operating System :: POSIX
Classifier: Programming Language :: Python :: 2 :: Only
Classifier: Topic :: Utilities
Classifier: Topic :: Communications :: Email :: Address Book
Requires: lxml
Requires: vobject
Requires: requests
Requires: urwid
Requires: pyxdg
